qurix/sample/package/__init__.py
qurix/sample/package/__version__.py
qurix/sample/package/client.py
release/set_version.py
tests/__init__.py
tests/test_client.py
qurix_sample_package-0.5.0.dist-info/METADATA
qurix_sample_package-0.5.0.dist-info/WHEEL
qurix_sample_package-0.5.0.dist-info/top_level.txt
qurix_sample_package-0.5.0.dist-info/RECORD
